{
  "$schema": "https://biomejs.dev/schemas/2.3.8/schema.json",
  "vcs": {
    "enabled": true,
    "clientKind": "git",
    "useIgnoreFile": true
  },
  "files": {
    "ignoreUnknown": false,
    "includes": ["**", "!node_modules", "!dist", "!build"]
  },
  "formatter": {
    "enabled": true,
    "indentStyle": "space",
    "indentWidth": 2,
    "lineEnding": "lf"
  },
  "linter": {
    "enabled": true,
    "rules": {
      "recommended": true,
      "suspicious": {
        "noDocumentCookie": "off",
        "noExplicitAny": "off"
      },
      "a11y": {
        "useKeyWithClickEvents": "off",
        "noStaticElementInteractions": "off"
      },
      "correctness": {
        "noUnusedImports": "off",
        "noUnusedVariables": "off"
      },
      "complexity": {
        "noUselessEscapeInRegex": "off"
      }
    }
  },
  "javascript": {
    "formatter": {
      "quoteStyle": "single",
      "semicolons": "always"
    }
  },
  "css": {
    "linter": {
      "enabled": true
    },
    "parser": {
      "tailwindDirectives": true
    }
  },
  "assist": {
    "enabled": true,
    "actions": {
      "source": {
        "organizeImports": "off"
      }
    }
  }
}
